odoo10_addon_shopinvader_contact_company-10.0.1.0.0.99.dev8-py3.8-nspkg.pth
odoo/addons/shopinvader_contact_company/README.rst
odoo/addons/shopinvader_contact_company/__init__.py
odoo/addons/shopinvader_contact_company/__manifest__.py
odoo/addons/shopinvader_contact_company/i18n/shopinvader_contact_company.pot
odoo/addons/shopinvader_contact_company/readme/CONTRIBUTORS.rst
odoo/addons/shopinvader_contact_company/readme/DESCRIPTION.rst
odoo/addons/shopinvader_contact_company/services/__init__.py
odoo/addons/shopinvader_contact_company/services/address.py
odoo/addons/shopinvader_contact_company/static/description/index.html
odoo/addons/shopinvader_contact_company/tests/__init__.py
odoo/addons/shopinvader_contact_company/tests/test_address.py
odoo10_addon_shopinvader_contact_company-10.0.1.0.0.99.dev8.dist-info/METADATA
odoo10_addon_shopinvader_contact_company-10.0.1.0.0.99.dev8.dist-info/WHEEL
odoo10_addon_shopinvader_contact_company-10.0.1.0.0.99.dev8.dist-info/namespace_packages.txt
odoo10_addon_shopinvader_contact_company-10.0.1.0.0.99.dev8.dist-info/top_level.txt
odoo10_addon_shopinvader_contact_company-10.0.1.0.0.99.dev8.dist-info/RECORD
